MANIFEST.in
setup.py
django_faces/__init__.py
django_faces/middleware.py
django_faces/models.py
django_faces/settings.py
django_faces/tests.py
django_faces/testsettings.py
django_faces/utils.py
django_faces/views.py
django_faces.egg-info/PKG-INFO
django_faces.egg-info/SOURCES.txt
django_faces.egg-info/dependency_links.txt
django_faces.egg-info/not-zip-safe
django_faces.egg-info/requires.txt
django_faces.egg-info/top_level.txt
django_faces/management/__init__.py
django_faces/management/commands/__init__.py
django_faces/management/commands/drop_faces_cache.py
django_faces/migrations/0001_initial.py
django_faces/migrations/__init__.py
django_faces/templates/faces/author_block.html
django_faces/templates/faces/avatar.html
django_faces/templatetags/__init__.py
django_faces/templatetags/faces_tags.py