Metadata-Version: 1.0
Name: django-faces
Version: 0.2.1
Summary: Django application for nonintrusive avatar support.It uses site's URL and user's email for autodiscovery.
Home-page: http://github.com/svetlyak40wt/django-faces/
Author: Alexander Artemenko
Author-email: svetlyak.40wt@gmail.com
License: New BSD License
Keywords: django apps avatar pavatar gravatar favicon
Platform: UNKNOWN
Classifier: Development Status :: 2 - Pre-Alpha
Classifier: Environment :: Plugins
Classifier: Framework :: Django
Classifier: Intended Audience :: Developers
Classifier: License :: OSI Approved :: BSD License
Classifier: Programming Language :: Python
Classifier: Topic :: Software Development :: Libraries :: Python Modules
